{
  "$schema": "https://developer.microsoft.com/json-schemas/fabric/item/report/definition/visualContainer/2.5.0/schema.json",
  "name": "c37e045d9df181bdd258",
  "position": {
    "x": 1.791044776119403,
    "y": 69.850746268656721,
    "z": 1000,
    "height": 12.53731343283582,
    "width": 1273.4328358208954,
    "tabOrder": 1000
  },
  "visual": {
    "visualType": "shape",
    "objects": {
      "shape": [
        {
          "properties": {
            "tileShape": {
              "expr": {
                "Literal": {
                  "Value": "'line'"
                }
              }
            }
          }
        }
      ],
      "rotation": [
        {
          "properties": {
            "shapeAngle": {
              "expr": {
                "Literal": {
                  "Value": "0L"
                }
              }
            }
          }
        }
      ]
    },
    "drillFilterOtherVisuals": true
  },
  "parentGroupName": "c1ea9bf67365d01303b7",
  "howCreated": "InsertVisualButton"
}